pyramid_debugauth/__init__.py
pyramid_debugauth/tests.py
pyramid_debugauth-0.2.0.dist-info/DESCRIPTION.rst
pyramid_debugauth-0.2.0.dist-info/METADATA
pyramid_debugauth-0.2.0.dist-info/RECORD
pyramid_debugauth-0.2.0.dist-info/WHEEL
pyramid_debugauth-0.2.0.dist-info/metadata.json
pyramid_debugauth-0.2.0.dist-info/top_level.txt
