Metadata-Version: 2.0
Name: pyramid-debugauth
Version: 0.2.0
Summary: Debug Authentication Policy for Pyramid
Home-page: https://github.com/pior/pyramid_debugauth
Author: Pior Bastida
Author-email: pior@pbastida.net
License: BSD-derived (http://www.repoze.org/LICENSE.txt)
Keywords: wsgi pylons pyramid auth authentication debug
Platform: UNKNOWN
Classifier: Development Status :: 4 - Beta
Classifier: Intended Audience :: Developers
Classifier: Programming Language :: Python
Classifier: Programming Language :: Python :: 2
Classifier: Programming Language :: Python :: 2.7
Classifier: Framework :: Pyramid
Classifier: Topic :: Internet :: WWW/HTTP :: WSGI
Provides-Extra: dev
Requires-Dist: nose; extra == 'dev'
Requires-Dist: nose-parameterized; extra == 'dev'
Requires-Dist: nosexcover; extra == 'dev'
Requires-Dist: coverage; extra == 'dev'
Requires-Dist: mock; extra == 'dev'
Requires-Dist: webtest; extra == 'dev'
Requires-Dist: pyramid; extra == 'dev'
Requires-Dist: readme; extra == 'dev'
Requires-Dist: twine; extra == 'dev'
Provides-Extra: docs
Requires-Dist: Sphinx; extra == 'docs'
Requires-Dist: sphinxcontrib-httpdomainlivereload (==1.0.1); extra == 'docs'
